<?xml version="1.0" encoding="UTF-8" ?>
<!DOCTYPE struts PUBLIC
"-//Apache Software Foundation//DTD Struts Configuration 2.0//EN"
"http://struts.apache.org/dtds/struts-2.0.dtd">
<struts>

    <package name="orderServiceDefault" extends="struts-default">
        <action name="viewOrderAction" class="viewOrderAction">
            <result name="error">error.jsp</result>
            <result name="success">vieworders.jsp</result>
        </action>
        <action name="modifyOrderAction" class="modifyOrderAction">
            <result name="error">error.jsp</result>
            <result name="success">createdelivery.jsp</result>
        </action>
    </package>

</struts>